LICENSE
README.md
setup.py
twitter_stream.py
twitter_stream.py.egg-info/PKG-INFO
twitter_stream.py.egg-info/SOURCES.txt
twitter_stream.py.egg-info/dependency_links.txt
twitter_stream.py.egg-info/requires.txt
twitter_stream.py.egg-info/top_level.txt