Metadata-Version: 2.1
Name: twitter-stream.py
Version: 0.8.8
Summary: Python Client For Twitter Streaming API v2
Home-page: https://github.com/twitivity/twitter-stream.py
Author: Saadman Rafat
Author-email: saadmanhere@gmail.com
License: MIT
Platform: UNKNOWN
Classifier: License :: OSI Approved :: MIT License
Classifier: Programming Language :: Python
Classifier: Programming Language :: Python :: 3.6
Classifier: Programming Language :: Python :: 3.7
Classifier: Programming Language :: Python :: 3.8
Classifier: Programming Language :: Python :: 3.9
Classifier: Programming Language :: Python :: 3.10
Classifier: Programming Language :: Python :: Implementation :: CPython
Classifier: Programming Language :: Python :: Implementation :: PyPy
Requires-Python: >=3.6.0
License-File: LICENSE
